{
  "_license": {
    "copyright": "Copyright 2026 Ingolf Lohmann",
    "rights_holder": "Ingolf Lohmann",
    "license": "CC-BY-NC-ND-4.0",
    "license_text_ref": "LICENSES/CC-BY-NC-ND-4.0.txt",
    "classification": "evidence_json"
  },
  "schema": "qikvrt_v32_windows_command_start_json_escape_verification_report",
  "created_utc": "2026-06-20T13:09:44Z",
  "status": "FINAL_ARTIFACT_DELIVERY_AUTHORIZED_BY_PRODUCT_OWNER_OVERRIDE",
  "windows_command_start_json_escape_gate": "PASS",
  "field_failure_pattern_rejected": true,
  "artifact_delivery_allowed": true,
  "external_evidence_claims": false
}
