{
  "stub_state": true,
  "_license": {
    "copyright": "Copyright 2026 Ingolf Lohmann",
    "rights_holder": "Ingolf Lohmann",
    "license": "CC-BY-NC-ND-4.0",
    "license_text_ref": "LICENSES/CC-BY-NC-ND-4.0.txt",
    "classification": "runtime_volatile_state_json"
  },
  "schema": "qikvrt_runtime_state_pre_required_files_bootstrap_v44",
  "path": "runtime/DEPENDENCIES.json",
  "classification": "VOLATILE_RUNTIME_STATE",
  "immutable_release_constant": false,
  "excluded_from_sha256sums": true,
  "must_exist_before_required_files_check": true,
  "last_bootstrap_utc": "2026-06-20T14:48:09Z",
  "must_exist_in_delivery_zip": true,
  "materialized_or_verified_utc": "2026-06-20T14:47:15Z"
}
